description_indexer/__init__.py
description_indexer/configurator.py
description_indexer/delete.py
description_indexer/utils.py
description_indexer/inputs/arclight.py
description_indexer/inputs/aspace.py
description_indexer/models/arclight.py
description_indexer/models/description.py
description_indexer/outputs/arclight.py
description_indexer-0.0.4.dist-info/LICENSE
description_indexer-0.0.4.dist-info/METADATA
description_indexer-0.0.4.dist-info/WHEEL
description_indexer-0.0.4.dist-info/entry_points.txt
description_indexer-0.0.4.dist-info/top_level.txt
description_indexer-0.0.4.dist-info/RECORD
