Metadata-Version: 2.1
Name: description-indexer
Version: 0.0.4
Summary: A tool for working with archival description for public access.
Home-page: https://github.com/UAlbanyArchives/description_indexer
Author: Gregory Wiedeman
Author-email: gwiedeman@albany.edu
Classifier: Programming Language :: Python :: 3
Classifier: License :: OSI Approved :: MIT License
Classifier: Operating System :: OS Independent
Requires-Python: >=3.7
License-File: LICENSE
Requires-Dist: archivessnake (<1,>=0.9.1)
Requires-Dist: black (<23,>=22.1.0)
Requires-Dist: iso-639 (<1,>=0.4.5)
Requires-Dist: pysolr (<4,>=3.9.0)
Requires-Dist: pyyaml (>=6.0<7)
Requires-Dist: requests (<3,>=2.28.1)
